Router_FSM/router_fsm.v
module router_fsm (
  input 		clock,
  input 		resetn,
  input 		pkt_valid,
  input			parity_done,
  input [1:0]	data_in,
  input 		soft_reset_0,
  input 		soft_reset_1,
  input 		soft_reset_2,
  input 		fifo_full,
  input 		low_pkt_valid,
  input 		fifo_empty_0,
  input			fifo_empty_1,
  input 		fifo_empty_2,
  
  output 		busy,
  output		detect_add,
  output		ld_state,
  output 		laf_state,
  output		full_state,
  output 		write_enb_reg,
  output		rst_int_reg,
  output		lfd_state
);
  
  reg [2:0]state, next_state;
  
  parameter DECODE_ADDRESS		= 	3'b000,
  			LOAD_FIRST_DATA		=	3'b001,
  			LOAD_DATA			=	3'b010,
  			LOAD_PARITY			=	3'b011,
  			FIFO_FULL_STATE		=	3'b100,
  			LOAD_AFTER_FULL		=	3'b101,
  			WAIT_TILL_EMPTY		=	3'b110,
  			CHECK_PARITY_ERROR	=	3'b111;
  
  // State Change Logic
  always @ (*)
    begin
      case (state)
        DECODE_ADDRESS: next_state = ((pkt_valid && (data_in[1:0] == 2'b00) && fifo_empty_0)|
                                      (pkt_valid && (data_in[1:0] == 2'b01) && fifo_empty_1)| 
                                      (pkt_valid && (data_in[1:0] == 2'b10) && fifo_empty_2)) ? LOAD_FIRST_DATA : 
          ((pkt_valid && (data_in[1:0] == 2'b00) && !fifo_empty_0)|
           (pkt_valid && (data_in[1:0] == 2'b01) && !fifo_empty_1)| 
           (pkt_valid && (data_in[1:0] == 2'b10) && !fifo_empty_2)) ? WAIT_TILL_EMPTY : DECODE_ADDRESS;
        
        LOAD_FIRST_DATA: next_state <= LOAD_DATA;
        LOAD_DATA: next_state <= (fifo_full) ? FIFO_FULL_STATE : (!fifo_full && !pkt_valid) ? LOAD_PARITY : LOAD_DATA;
        LOAD_PARITY: next_state <= CHECK_PARITY_ERROR;
        FIFO_FULL_STATE: next_state <= (fifo_full) ? FIFO_FULL_STATE : LOAD_AFTER_FULL;
        LOAD_AFTER_FULL: next_state <= (parity_done) ? DECODE_ADDRESS : 
          							   (!parity_done && low_pkt_valid) ? LOAD_PARITY : 
          							   (!parity_done && !low_pkt_valid) ? LOAD_DATA : LOAD_AFTER_FULL;
        WAIT_TILL_EMPTY: next_state <= (((data_in[1:0] == 2'b00) && fifo_empty_0)|
                                       ((data_in[1:0] == 2'b01) && fifo_empty_1)| 
                                        ((data_in[1:0] == 2'b10) && fifo_empty_2)) ? LOAD_FIRST_DATA : WAIT_TILL_EMPTY;
        CHECK_PARITY_ERROR: next_state <= (fifo_full) ? FIFO_FULL_STATE : DECODE_ADDRESS;
        default next_state <= DECODE_ADDRESS;
      endcase
    end
  
  // State Transition
  always @ (posedge clock)
    begin
      if (!resetn || (soft_reset_0 || soft_reset_1 || soft_reset_2))
        state <= DECODE_ADDRESS;
      else
        state <= next_state;
    end
  
  // Ouputs based on current states
  assign busy = ((state == LOAD_DATA) || (state == DECODE_ADDRESS)) ? 1'b0 : 1'b1;
  assign detect_add = (state == DECODE_ADDRESS);
  assign ld_state = (state == LOAD_DATA);
  assign laf_state= (state == LOAD_AFTER_FULL);
  assign full_state = (state == FIFO_FULL_STATE);
  assign write_enb_reg = ((state == LOAD_DATA) || (state == LOAD_PARITY) || (state == LOAD_AFTER_FULL));
  assign rst_int_reg = (state == CHECK_PARITY_ERROR);
  assign lfd_state = (state == LOAD_FIRST_DATA);;

endmodule

VIVADO Files/router_fsm/router_fsm.srcs/sources_1/new/router_fms_tb.v
`timescale 1ns / 1ps

module router_fsm_tb;
  // Inputs
  reg clock;
  reg resetn;
  reg pkt_valid;
  reg parity_done;
  reg [1:0] data_in;
  reg soft_reset_0;
  reg soft_reset_1;
  reg soft_reset_2;
  reg fifo_full;
  reg low_pkt_valid;
  reg fifo_empty_0;
  reg fifo_empty_1;
  reg fifo_empty_2;

  // Outputs
  wire busy;
  wire detect_add;
  wire ld_state;
  wire laf_state;
  wire full_state;
  wire write_enb_reg;
  wire rst_int_reg;
  wire lfd_state;

  // Instantiate the DUT (Design Under Test)
  router_fsm dut (
    .clock(clock),
    .resetn(resetn),
    .pkt_valid(pkt_valid),
    .parity_done(parity_done),
    .data_in(data_in),
    .soft_reset_0(soft_reset_0),
    .soft_reset_1(soft_reset_1),
    .soft_reset_2(soft_reset_2),
    .fifo_full(fifo_full),
    .low_pkt_valid(low_pkt_valid),
    .fifo_empty_0(fifo_empty_0),
    .fifo_empty_1(fifo_empty_1),
    .fifo_empty_2(fifo_empty_2),
    .busy(busy),
    .detect_add(detect_add),
    .ld_state(ld_state),
    .laf_state(laf_state),
    .full_state(full_state),
    .write_enb_reg(write_enb_reg),
    .rst_int_reg(rst_int_reg),
    .lfd_state(lfd_state)
  );

  // Clock generation
  always #5 clock = ~clock;
  
  // VCD Files
  initial begin
   $dumpfile("dump.vcd");
   $dumpvars;
  end

  // Initial values
  initial begin
    clock = 0;
    resetn = 1;
    pkt_valid = 0;
    parity_done = 0;
    data_in = 2'b00;
    soft_reset_0 = 0;
    soft_reset_1 = 0;
    soft_reset_2 = 0;
    fifo_full = 0;
    low_pkt_valid = 0;
    fifo_empty_0 = 1;
    fifo_empty_1 = 1;
    fifo_empty_2 = 1;

    #5 resetn = 0; // Assert resetn
    #10 resetn = 1; // De-assert resetn

    // Test scenario 1: Load first data
    pkt_valid = 1;
    data_in = 2'b00;
    #50;
    pkt_valid = 0; // Finish loading data
    #20;

    // Test scenario 2: FIFO full state
    pkt_valid = 1;
    data_in = 2'b00;
    fifo_empty_0 = 0; // Simulate FIFO full
    #50;
    fifo_empty_0 = 1;
    #20;

    // Test scenario 1: Load first data - Address 0, FIFO 0 is empty
  pkt_valid = 1;
  data_in = 2'b00;
  fifo_empty_0 = 1;
  #50;
  pkt_valid = 0; // Finish loading data
  #20;

  // Test scenario 2: Load first data - Address 1, FIFO 1 is empty
  pkt_valid = 1;
  data_in = 2'b01;
  fifo_empty_1 = 1;
  #50;
  pkt_valid = 0; // Finish loading data
  #20;

  // Test scenario 3: Load first data - Address 2, FIFO 2 is empty
  pkt_valid = 1;
  data_in = 2'b10;
  fifo_empty_2 = 1;
  #50;
  pkt_valid = 0; // Finish loading data
  #20;

  // Test scenario 4: Wait till FIFO becomes empty
  pkt_valid = 1;
  data_in = 2'b01;
  fifo_empty_1 = 0; // FIFO not empty
  #50;
  fifo_empty_1 = 1; // FIFO becomes empty
  #20;
  pkt_valid = 0; // Finish loading data
  #20;

  // Test scenario 5: FIFO Full state - FIFO 0 is full
  pkt_valid = 1;
  data_in = 2'b00;
  fifo_empty_0 = 0; // FIFO not empty
  fifo_full = 1;   // FIFO full
  #50;
  fifo_empty_0 = 1; // FIFO becomes empty
  #20;

  // Test scenario 6: Parity error detected
  pkt_valid = 1;
  data_in = 2'b11; // Invalid address
  fifo_empty_0 = 1;
  #50;
  pkt_valid = 0; // Finish loading data
  #20;

  // Test scenario 7: Load data, then parity, then load after full
  pkt_valid = 1;
  data_in = 2'b01;
  fifo_empty_1 = 1;
  #50;
  pkt_valid = 0; // Finish loading data
  #20;
  // Parity done
  parity_done = 1;
  #50;
  // Load data after FIFO was full
  fifo_full = 1;
  #50;
  fifo_full = 0;
  #20;

  // Test scenario 8: Check reset behavior
  soft_reset_0 = 1;
  #20;
  soft_reset_0 = 0;
  #50;
  soft_reset_1 = 1;
  #20;
  soft_reset_1 = 0;
  #50;
  soft_reset_2 = 1;
  #20;
  soft_reset_2 = 0;
  #50;

    #100 $finish; // Finish simulation
  end

  // Monitor the state changes (optional, for debugging purposes)
  always @(posedge clock) begin
    $display("Current state: %b", dut.state);
    $display("Next state: %b", dut.next_state);
  end

endmodule

VIVADO Files/router_fsm/router_fsm.sim/sim_1/behav/xsim/dump.vcd
$date
   Fri Aug 11 17:45:30 2023
$end
$version
  2022.2
$end
$timescale
  1ps
$end
$scope module router_fsm_tb $end
$var reg 1 ! clock $end
$var reg 1 " resetn $end
$var reg 1 # pkt_valid $end
$var reg 1 $ parity_done $end
$var reg 2 % data_in [1:0] $end
$var reg 1 & soft_reset_0 $end
$var reg 1 ' soft_reset_1 $end
$var reg 1 ( soft_reset_2 $end
$var reg 1 ) fifo_full $end
$var reg 1 * low_pkt_valid $end
$var reg 1 + fifo_empty_0 $end
$var reg 1 , fifo_empty_1 $end
$var reg 1 - fifo_empty_2 $end
$var wire 1 . busy $end
$var wire 1 / detect_add $end
$var wire 1 0 ld_state $end
$var wire 1 1 laf_state $end
$var wire 1 2 full_state $end
$var wire 1 3 write_enb_reg $end
$var wire 1 4 rst_int_reg $end
$var wire 1 5 lfd_state $end
$scope module dut $end
$var wire 1 6 clock $end
$var wire 1 7 resetn $end
$var wire 1 8 pkt_valid $end
$var wire 1 9 parity_done $end
$var wire 2 : data_in [1:0] $end
$var wire 1 ; soft_reset_0 $end
$var wire 1 < soft_reset_1 $end
$var wire 1 = soft_reset_2 $end
$var wire 1 > fifo_full $end
$var wire 1 ? low_pkt_valid $end
$var wire 1 @ fifo_empty_0 $end
$var wire 1 A fifo_empty_1 $end
$var wire 1 B fifo_empty_2 $end
$var wire 1 . busy $end
$var wire 1 / detect_add $end
$var wire 1 0 ld_state $end
$var wire 1 1 laf_state $end
$var wire 1 2 full_state $end
$var wire 1 3 write_enb_reg $end
$var wire 1 4 rst_int_reg $end
$var wire 1 5 lfd_state $end
$var reg 3 C state [2:0] $end
$var reg 3 D next_state [2:0] $end
$upscope $end
$upscope $end
$enddefinitions $end
#0
$dumpvars
0!
1"
0#
0$
b0 %
0&
0'
0(
0)
0*
1+
1,
1-
x.
x/
x0
x1
x2
x3
x4
x5
06
17
08
09
b0 :
0;
0<
0=
0>
0?
1@
1A
1B
bx C
b0 D
$end
#5000
1!
0"
0.
1/
00
01
02
03
04
05
16
07
b0 C
b0 D
#10000
0!
06
#15000
1!
1"
1#
b0 %
1.
0/
00
01
02
03
04
15
16
17
18
b1 C
b10 D
#20000
0!
06
#25000
1!
0.
0/
10
01
02
13
04
05
16
b10 C
b10 D
#30000
0!
06
#35000
1!
16
b10 C
#40000
0!
06
#45000
1!
16
b10 C
#50000
0!
06
#55000
1!
16
b10 C
#60000
0!
06
#65000
1!
0#
16
08
b10 C
b11 D
#70000
0!
06
#75000
1!
1.
0/
00
01
02
13
04
05
16
b11 C
b111 D
#80000
0!
06
#85000
1!
1#
b0 %
0+
1.
0/
00
01
02
03
14
05
16
18
0@
b111 C
b0 D
#90000
0!
06
#95000
1!
0.
1/
00
01
02
03
04
05
16
b0 C
b110 D
#100000
0!
06
#105000
1!
1.
0/
00
01
02
03
04
05
16
b110 C
b110 D
#110000
0!
06
#115000
1!
16
b110 C
#120000
0!
06
#125000
1!
16
b110 C
#130000
0!
06
#135000
1!
1+
16
1@
b110 C
b1 D
#140000
0!
06
#145000
1!
1.
0/
00
01
02
03
04
15
16
b1 C
b10 D
#150000
0!
06
#155000
1!
b0 %
0.
0/
10
01
02
13
04
05
16
b10 C
b10 D
#160000
0!
06
#165000
1!
16
b10 C
#170000
0!
06
#175000
1!
16
b10 C
#180000
0!
06
#185000
1!
16
b10 C
#190000
0!
06
#195000
1!
16
b10 C
#200000
0!
06
#205000
1!
0#
16
08
b10 C
b11 D
#210000
0!
06
#215000
1!
1.
0/
00
01
02
13
04
05
16
b11 C
b111 D
#220000
0!
06
#225000
1!
1#
b1 %
1.
0/
00
01
02
03
14
05
16
18
b1 :
b111 C
b0 D
#230000
0!
06
#235000
1!
0.
1/
00
01
02
03
04
05
16
b0 C
b1 D
#240000
0!
06
#245000
1!
1.
0/
00
01
02
03
04
15
16
b1 C
b10 D
#250000
0!
06
#255000
1!
0.
0/
10
01
02
13
04
05
16
b10 C
b10 D
#260000
0!
06
#265000
1!
16
b10 C
#270000
0!
06
#275000
1!
0#
16
08
b10 C
b11 D
#280000
0!
06
#285000
1!
1.
0/
00
01
02
13
04
05
16
b11 C
b111 D
#290000
0!
06
#295000
1!
1#
b10 %
1.
0/
00
01
02
03
14
05
16
18
b10 :
b111 C
b0 D
#300000
0!
06
#305000
1!
0.
1/
00
01
02
03
04
05
16
b0 C
b1 D
#310000
0!
06
#315000
1!
1.
0/
00
01
02
03
04
15
16
b1 C
b10 D
#320000
0!
06
#325000
1!
0.
0/
10
01
02
13
04
05
16
b10 C
b10 D
#330000
0!
06
#335000
1!
16
b10 C
#340000
0!
06
#345000
1!
0#
16
08
b10 C
b11 D
#350000
0!
06
#355000
1!
1.
0/
00
01
02
13
04
05
16
b11 C
b111 D
#360000
0!
06
#365000
1!
1#
b1 %
0,
1.
0/
00
01
02
03
14
05
16
18
b1 :
0A
b111 C
b0 D
#370000
0!
06
#375000
1!
0.
1/
00
01
02
03
04
05
16
b0 C
b110 D
#380000
0!
06
#385000
1!
1.
0/
00
01
02
03
04
05
16
b110 C
b110 D
#390000
0!
06
#395000
1!
16
b110 C
#400000
0!
06
#405000
1!
16
b110 C
#410000
0!
06
#415000
1!
1,
16
1A
b110 C
b1 D
#420000
0!
06
#425000
1!
1.
0/
00
01
02
03
04
15
16
b1 C
b10 D
#430000
0!
06
#435000
1!
0#
0.
0/
10
01
02
13
04
05
16
08
b10 C
b11 D
#440000
0!
06
#445000
1!
1.
0/
00
01
02
13
04
05
16
b11 C
b111 D
#450000
0!
06
#455000
1!
1#
b0 %
1)
0+
1.
0/
00
01
02
03
14
05
16
18
b0 :
1>
0@
b111 C
b100 D
#460000
0!
06
#465000
1!
1.
0/
00
01
12
03
04
05
16
b100 C
b100 D
#470000
0!
06
#475000
1!
16
b100 C
#480000
0!
06
#485000
1!
16
b100 C
#490000
0!
06
#495000
1!
16
b100 C
#500000
0!
06
#505000
1!
1+
16
1@
b100 C
b100 D
#510000
0!
06
#515000
1!
16
b100 C
#520000
0!
06
#525000
1!
b11 %
16
b11 :
b100 C
b100 D
#530000
0!
06
#535000
1!
16
b100 C
#540000
0!
06
#545000
1!
16
b100 C
#550000
0!
06
#555000
1!
16
b100 C
#560000
0!
06
#565000
1!
16
b100 C
#570000
0!
06
#575000
1!
0#
16
08
b100 C
b100 D
#580000
0!
06
#585000
1!
16
b100 C
#590000
0!
06
#595000
1!
1#
b1 %
16
18
b1 :
b100 C
b100 D
#600000
0!
06
#605000
1!
16
b100 C
#610000
0!
06
#615000
1!
16
b100 C
#620000
0!
06
#625000
1!
16
b100 C
#630000
0!
06
#635000
1!
16
b100 C
#640000
0!
06
#645000
1!
0#
16
08
b100 C
b100 D
#650000
0!
06
#655000
1!
16
b100 C
#660000
0!
06
#665000
1!
1$
16
19
b100 C
b100 D
#670000
0!
06
#675000
1!
16
b100 C
#680000
0!
06
#685000
1!
16
b100 C
#690000
0!
06
#695000
1!
16
b100 C
#700000
0!
06
#705000
1!
16
b100 C
#710000
0!
06
#715000
1!
16
b100 C
#720000
0!
06
#725000
1!
16
b100 C
#730000
0!
06
#735000
1!
16
b100 C
#740000
0!
06
#745000
1!
16
b100 C
#750000
0!
06
#755000
1!
16
b100 C
#760000
0!
06
#765000
1!
0)
16
0>
b100 C
b101 D
#770000
0!
06
#775000
1!
1.
0/
00
11
02
13
04
05
16
b101 C
b0 D
#780000
0!
06
#785000
1!
1&
0.
1/
00
01
02
03
04
05
16
1;
b0 C
b0 D
#790000
0!
06
#795000
1!
16
b0 C
#800000
0!
06
#805000
1!
0&
16
0;
b0 C
#810000
0!
06
#815000
1!
16
b0 C
#820000
0!
06
#825000
1!
16
b0 C
#830000
0!
06
#835000
1!
16
b0 C
#840000
0!
06
#845000
1!
16
b0 C
#850000
0!
06
#855000
1!
1'
16
1<
b0 C
#860000
0!
06
#865000
1!
16
b0 C
#870000
0!
06
#875000
1!
0'
16
0<
b0 C
#880000
0!
06
#885000
1!
16
b0 C
#890000
0!
06
#895000
1!
16
b0 C
#900000
0!
06
#905000
1!
16
b0 C
#910000
0!
06
#915000
1!
16
b0 C
#920000
0!
06
#925000
1!
1(
16
1=
b0 C
#930000
0!
06
#935000
1!
16
b0 C
#940000
0!
06
#945000
1!
0(
16
0=
b0 C
#950000
0!
06
#955000
1!
16
b0 C
#960000
0!
06
#965000
1!
16
b0 C
#970000
0!
06
#975000
1!
16
b0 C
#980000
0!
06
#985000
1!
16
b0 C
#990000
0!
06
#995000
1!
16
b0 C
